tilmedia/__init__.py
tilmedia/_internals.py
tilmedia/batchcaller.py
tilmedia/convert.py
tilmedia/core.cpython-312-x86_64-linux-gnu.so
tilmedia/core.pyi
tilmedia/datacontainer.py
tilmedia/exceptions.py
tilmedia/gas.py
tilmedia/general.py
tilmedia/liquid.py
tilmedia/moistair.py
tilmedia/properties.py
tilmedia/vlefluid.py
tilmedia-2025.2.dist-info/METADATA
tilmedia-2025.2.dist-info/WHEEL
tilmedia-2025.2.dist-info/top_level.txt
tilmedia-2025.2.dist-info/RECORD
tilmedia-2025.2.dist-info/licenses/LICENSE.txt
tilmedia-2025.2.dist-info/licenses/Third-Party-License.txt
