Metadata-Version: 2.4
Name: tilmedia
Version: 2025.2
Summary: Substance properties for incompressible liquids, ideal gases, real fluids and mixtures
Home-page: https://www.tlk-thermo.com/en/software/tilmedia-suite
Author: TLK-Thermo GmbH
Author-email: tilmedia@tlk-thermo.com
License: BSD
Keywords: thermophysical thermodynamic fluid properties gas liquid mixtures substances media
Classifier: Programming Language :: Python :: 3
Classifier: Programming Language :: Python :: 3.8
Classifier: Programming Language :: Python :: 3.9
Classifier: Programming Language :: Python :: 3.10
Classifier: Programming Language :: Python :: 3.11
Classifier: Programming Language :: Python :: 3.12
Classifier: Development Status :: 5 - Production/Stable
Classifier: Operating System :: Microsoft :: Windows
Classifier: Operating System :: POSIX :: Linux
Classifier: Natural Language :: English
Classifier: Topic :: Scientific/Engineering
Classifier: Topic :: Scientific/Engineering :: Physics
Classifier: Topic :: Scientific/Engineering :: Chemistry
License-File: LICENSE.txt
License-File: Third-Party-License.txt
Requires-Dist: numpy
Dynamic: author
Dynamic: author-email
Dynamic: classifier
Dynamic: description
Dynamic: description-content-type
Dynamic: home-page
Dynamic: keywords
Dynamic: license
Dynamic: license-file
Dynamic: requires-dist
Dynamic: summary
